vat_moss/__init__.py
vat_moss/billing_address.py
vat_moss/declared_residence.py
vat_moss/errors.py
vat_moss/exchange_rates.py
vat_moss/geoip2.py
vat_moss/id.py
vat_moss/phone_number.py
vat_moss/rates.py
vat_moss_forked-2020.3.20.0.11.0.dist-info/LICENSE
vat_moss_forked-2020.3.20.0.11.0.dist-info/METADATA
vat_moss_forked-2020.3.20.0.11.0.dist-info/WHEEL
vat_moss_forked-2020.3.20.0.11.0.dist-info/top_level.txt
vat_moss_forked-2020.3.20.0.11.0.dist-info/RECORD
